[{"realpos":1,"label_name":"","topic_flag":1,"word_scheme":"#被盗国保琉璃竟在闲鱼公开售卖#","emoticon":"","word":"被盗国保琉璃竟在闲鱼公开售卖","num":1055456,"flag":0,"note":"被盗国保琉璃竟在闲鱼公开售卖","rank":0},{"icon_desc_color":"#ff3852","label_name":"新","small_icon_desc":"新","small_icon_desc_color":"#ff3852","word_scheme":"爱奇艺股价","word":"爱奇艺股价","emoticon":"","icon":"https://simg.s.weibo.com/moter/flags/1_0.png","icon_width":24,"icon_height":24,"num":743271,"flag":1,"topic_flag":0,"note":"爱奇艺股价","icon_desc":"新","realpos":2,"rank":1},{"icon_desc_color":"#ff3852","label_name":"新","small_icon_desc":"新","small_icon_desc_color":"#ff3852","word_scheme":"#绿色低碳发展迈入法典时代#","word":"绿色低碳发展迈入法典时代","emoticon":"","icon":"https://simg.s.weibo.com/moter/flags/1_0.png","icon_width":24,"icon_height":24,"num":629045,"flag":1,"topic_flag":1,"note":"绿色低碳发展迈入法典时代","icon_desc":"新","realpos":3,"rank":2},{"icon_type":"jian","topic_flag":1,"emoticon":"","monitors":{"pc":[{"type":"","pc_click":"","pc_show":""},{"type":"","pc_click":"","pc_show":""},{"monitor_name":"C2S","type":"C2S","pc_click":"http://api.weibo.cn/2/h5/comonitor?mo=__OS__&log=this_is_empty_third_party_monitor_url&action=click&adid=328308&search=%23%E6%B5%B7%E5%B0%94%E6%99%BA%E6%85%A7%E5%AE%B6%E5%BA%AD%E5%AE%9A%E5%88%B6%E4%BD%A0%E7%9A%84AI%E7%94%9F%E6%B4%BB%23","pc_show":"http://api.weibo.cn/2/h5/comonitor?mo=__OS__&log=this_is_empty_third_party_monitor_url&action=show&adid=328308&search=%23%E6%B5%B7%E5%B0%94%E6%99%BA%E6%85%A7%E5%AE%B6%E5%BA%AD%E5%AE%9A%E5%88%B6%E4%BD%A0%E7%9A%84AI%E7%94%9F%E6%B4%BB%23"}],"app":[{"third_party_click":"","type":"","third_party_show":""},{"third_party_click":"","type":"","third_party_show":""},{"monitor_name":"C2S","third_party_click":"http://api.weibo.cn/2/h5/comonitor?mo=__OS__&log=this_is_empty_third_party_monitor_url&action=click&adid=328308&search=%23%E6%B5%B7%E5%B0%94%E6%99%BA%E6%85%A7%E5%AE%B6%E5%BA%AD%E5%AE%9A%E5%88%B6%E4%BD%A0%E7%9A%84AI%E7%94%9F%E6%B4%BB%23","type":"C2S","third_party_show":"http://api.weibo.cn/2/h5/comonitor?mo=__OS__&log=this_is_empty_third_party_monitor_url&action=show&adid=328308&search=%23%E6%B5%B7%E5%B0%94%E6%99%BA%E6%85%A7%E5%AE%B6%E5%BA%AD%E5%AE%9A%E5%88%B6%E4%BD%A0%E7%9A%84AI%E7%94%9F%E6%B4%BB%23"}]},"icon_width":24,"icon_height":24,"num":546372,"note":"海尔智慧家庭定制你的AI生活","icon_desc":"重磅","icon_desc_color":"#00b7ee","small_icon_desc":"商","small_icon_desc_color":"#00b7ee","word":"海尔智慧家庭定制你的AI生活","id":328308,"is_ad":1,"topic_ad":1,"dot_icon":1,"icon":"https://simg.s.weibo.com/imgtool/20241104_20241104_zhongbang_icon.png","rank":2},{"icon_desc_color":"#ff9406","label_name":"热","small_icon_desc":"热","small_icon_desc_color":"#ff9406","word_scheme":"#研究称第二次怀孕会继续重塑大脑#","word":"研究称第二次怀孕会继续重塑大脑","emoticon":"","icon":"https://simg.s.weibo.com/moter/flags/2_0.png","icon_width":24,"icon_height":24,"num":507466,"flag":2,"topic_flag":1,"note":"研究称第二次怀孕会继续重塑大脑","icon_desc":"热","realpos":4,"rank":3},{"realpos":5,"label_name":"","topic_flag":0,"word_scheme":"微信 朋友圈编辑","emoticon":"","word":"微信 朋友圈编辑","num":216469,"flag":0,"note":"微信 朋友圈编辑","rank":4},{"realpos":6,"label_name":"新","topic_flag":0,"word_scheme":"逐玉","emoticon":"","icon":"https://simg.s.weibo.com/moter/flags/1_0.png","icon_width":24,"icon_height":24,"num":213168,"flag":1,"note":"逐玉","icon_desc":"新","icon_desc_color":"#ff3852","small_icon_desc":"新","small_icon_desc_color":"#ff3852","word":"逐玉","flag_desc":"剧集","rank":5},{"icon_type":"jian","topic_flag":1,"emoticon":"","monitors":{"pc":[{"type":"","pc_click":"","pc_show":""},{"type":"","pc_click":"","pc_show":""},{"monitor_name":"C2S","type":"C2S","pc_click":"http://api.weibo.cn/2/h5/comonitor?mo=__OS__&log=this_is_empty_third_party_monitor_url&action=click&adid=328620&search=%23%E4%BA%B2%E7%88%B1%E7%9A%84%E5%AE%A2%E6%A0%88%E5%90%B8%E7%9D%9Bcp%E4%B8%8A%E7%BA%BF%23","pc_show":"http://api.weibo.cn/2/h5/comonitor?mo=__OS__&log=this_is_empty_third_party_monitor_url&action=show&adid=328620&search=%23%E4%BA%B2%E7%88%B1%E7%9A%84%E5%AE%A2%E6%A0%88%E5%90%B8%E7%9D%9Bcp%E4%B8%8A%E7%BA%BF%23"}],"app":[{"third_party_click":"","type":"","third_party_show":""},{"third_party_click":"","type":"","third_party_show":""},{"monitor_name":"C2S","third_party_click":"http://api.weibo.cn/2/h5/comonitor?mo=__OS__&log=this_is_empty_third_party_monitor_url&action=click&adid=328620&search=%23%E4%BA%B2%E7%88%B1%E7%9A%84%E5%AE%A2%E6%A0%88%E5%90%B8%E7%9D%9Bcp%E4%B8%8A%E7%BA%BF%23","type":"C2S","third_party_show":"http://api.weibo.cn/2/h5/comonitor?mo=__OS__&log=this_is_empty_third_party_monitor_url&action=show&adid=328620&search=%23%E4%BA%B2%E7%88%B1%E7%9A%84%E5%AE%A2%E6%A0%88%E5%90%B8%E7%9D%9Bcp%E4%B8%8A%E7%BA%BF%23"}]},"icon_width":24,"icon_height":24,"num":212919,"note":"亲爱的客栈吸睛cp上线","icon_desc":"官宣","icon_desc_color":"#00b7ee","small_icon_desc":"商","small_icon_desc_color":"#00b7ee","word":"亲爱的客栈吸睛cp上线","id":328620,"is_ad":1,"topic_ad":1,"dot_icon":1,"icon":"https://simg.s.weibo.com/20220424_search_ads_%E5%AE%98%E5%AE%A3.png","rank":5},{"realpos":7,"label_name":"","topic_flag":0,"word_scheme":"姓丁的有福了 丁永一","emoticon":"","word":"姓丁的有福了 丁永一","flag_desc":"剧集","num":212790,"flag":0,"note":"姓丁的有福了 丁永一","rank":6},{"icon_desc_color":"#ff3852","label_name":"新","small_icon_desc":"新","small_icon_desc_color":"#ff3852","word_scheme":"#这些两会好声音掷地有声#","word":"这些两会好声音掷地有声","emoticon":"","icon":"https://simg.s.weibo.com/moter/flags/1_0.png","icon_width":24,"icon_height":24,"num":206487,"flag":1,"topic_flag":1,"note":"这些两会好声音掷地有声","icon_desc":"新","realpos":8,"rank":7},{"realpos":9,"label_name":"","topic_flag":0,"word_scheme":"俞浅浅为什么不认识张凌赫田曦薇","emoticon":"","word":"俞浅浅为什么不认识张凌赫田曦薇","num":205722,"flag":0,"note":"俞浅浅为什么不认识张凌赫田曦薇","rank":8},{"realpos":10,"label_name":"","topic_flag":1,"word_scheme":"#取消家长护学岗让家校关系回归正轨#","emoticon":"","word":"取消家长护学岗让家校关系回归正轨","num":201584,"flag":0,"note":"取消家长护学岗让家校关系回归正轨","rank":9},{"icon_desc_color":"#ff3852","label_name":"新","small_icon_desc":"新","small_icon_desc_color":"#ff3852","word_scheme":"#荷兰回国认亲女子生父回应遗弃女儿#","word":"荷兰回国认亲女子生父回应遗弃女儿","emoticon":"","icon":"https://simg.s.weibo.com/moter/flags/1_0.png","icon_width":24,"icon_height":24,"num":199212,"flag":1,"topic_flag":1,"note":"荷兰回国认亲女子生父回应遗弃女儿","icon_desc":"新","realpos":11,"rank":10},{"realpos":12,"label_name":"","topic_flag":0,"word_scheme":"长期用小拇指托手机的后果","emoticon":"","word":"长期用小拇指托手机的后果","num":194857,"flag":0,"note":"长期用小拇指托手机的后果","rank":11},{"realpos":13,"label_name":"","topic_flag":0,"word_scheme":"严屹宽 双男主","emoticon":"","word":"严屹宽 双男主","num":153215,"flag":0,"note":"严屹宽 双男主","rank":12},{"realpos":14,"label_name":"","topic_flag":1,"word_scheme":"#母亲网购中药儿子吃后抽搐昏迷#","emoticon":"","word":"母亲网购中药儿子吃后抽搐昏迷","num":142407,"flag":0,"note":"母亲网购中药儿子吃后抽搐昏迷","rank":13},{"icon_desc_color":"#ff3852","label_name":"新","small_icon_desc":"新","small_icon_desc_color":"#ff3852","word_scheme":"随元青我恨你","word":"随元青我恨你","emoticon":"","icon":"https://simg.s.weibo.com/moter/flags/1_0.png","icon_width":24,"icon_height":24,"num":135004,"flag":1,"topic_flag":0,"note":"随元青我恨你","icon_desc":"新","realpos":15,"rank":14},{"icon_desc_color":"#ff3852","label_name":"新","small_icon_desc":"新","small_icon_desc_color":"#ff3852","word_scheme":"#24岁女研究生陪母抗癌后确诊肠癌#","word":"24岁女研究生陪母抗癌后确诊肠癌","emoticon":"","icon":"https://simg.s.weibo.com/moter/flags/1_0.png","icon_width":24,"icon_height":24,"num":133512,"flag":1,"topic_flag":1,"note":"24岁女研究生陪母抗癌后确诊肠癌","icon_desc":"新","realpos":16,"rank":15},{"icon_desc_color":"#ff3852","label_name":"新","small_icon_desc":"新","small_icon_desc_color":"#ff3852","word_scheme":"铁证 孙红雷刘宇宁","word":"铁证 孙红雷刘宇宁","emoticon":"","icon":"https://simg.s.weibo.com/moter/flags/1_0.png","icon_width":24,"icon_height":24,"num":133064,"flag":1,"topic_flag":0,"note":"铁证 孙红雷刘宇宁","icon_desc":"新","realpos":17,"rank":16},{"icon_desc_color":"#ff3852","label_name":"新","small_icon_desc":"新","small_icon_desc_color":"#ff3852","word_scheme":"#华为回应15599元折叠屏用3天黑屏#","word":"华为回应15599元折叠屏用3天黑屏","emoticon":"","icon":"https://simg.s.weibo.com/moter/flags/1_0.png","icon_width":24,"icon_height":24,"num":131954,"flag":1,"topic_flag":1,"note":"华为回应15599元折叠屏用3天黑屏","icon_desc":"新","realpos":18,"rank":17},{"realpos":19,"label_name":"","topic_flag":1,"word_scheme":"#中方向伊朗遇难学生家长援助20万美元#","emoticon":"","word":"中方向伊朗遇难学生家长援助20万美元","num":129357,"flag":0,"note":"中方向伊朗遇难学生家长援助20万美元","rank":18},{"icon_desc_color":"#ff3852","label_name":"新","small_icon_desc":"新","small_icon_desc_color":"#ff3852","word_scheme":"#阳光财险员工借项目垫资骗取百万元#","word":"阳光财险员工借项目垫资骗取百万元","emoticon":"","icon":"https://simg.s.weibo.com/moter/flags/1_0.png","icon_width":24,"icon_height":24,"num":123496,"flag":1,"topic_flag":1,"note":"阳光财险员工借项目垫资骗取百万元","icon_desc":"新","realpos":20,"rank":19},{"icon_desc_color":"#ff3852","label_name":"新","small_icon_desc":"新","small_icon_desc_color":"#ff3852","word_scheme":"#关晓彤紧急补救塌颅顶#","word":"关晓彤紧急补救塌颅顶","emoticon":"","icon":"https://simg.s.weibo.com/moter/flags/1_0.png","icon_width":24,"icon_height":24,"num":123415,"flag":1,"topic_flag":1,"note":"关晓彤紧急补救塌颅顶","icon_desc":"新","realpos":21,"rank":20},{"realpos":22,"label_name":"","topic_flag":0,"word_scheme":"爱情公寓是霍建华推荐娄艺潇演的","emoticon":"","word":"爱情公寓是霍建华推荐娄艺潇演的","flag_desc":"剧集","num":123325,"flag":0,"note":"爱情公寓是霍建华推荐娄艺潇演的","rank":21},{"icon_desc_color":"#ff3852","label_name":"新","small_icon_desc":"新","small_icon_desc_color":"#ff3852","word_scheme":"#7000元月薪种地不到一周已招满#","word":"7000元月薪种地不到一周已招满","emoticon":"","icon":"https://simg.s.weibo.com/moter/flags/1_0.png","icon_width":24,"icon_height":24,"num":122927,"flag":1,"topic_flag":1,"note":"7000元月薪种地不到一周已招满","icon_desc":"新","realpos":23,"rank":22},{"icon_desc_color":"#ff3852","label_name":"新","small_icon_desc":"新","small_icon_desc_color":"#ff3852","word_scheme":"#谢娜防了半天还是被套路了#","word":"谢娜防了半天还是被套路了","emoticon":"","icon":"https://simg.s.weibo.com/moter/flags/1_0.png","icon_width":24,"icon_height":24,"num":120306,"flag":1,"topic_flag":1,"note":"谢娜防了半天还是被套路了","icon_desc":"新","realpos":24,"rank":23},{"realpos":25,"label_name":"","topic_flag":1,"word_scheme":"#女子把过期牛奶给狗喝致其死亡#","emoticon":"","word":"女子把过期牛奶给狗喝致其死亡","num":110668,"flag":0,"note":"女子把过期牛奶给狗喝致其死亡","rank":24},{"realpos":26,"label_name":"新","topic_flag":0,"word_scheme":"76年的李维嘉像96年的付豪生的","emoticon":"","icon":"https://simg.s.weibo.com/moter/flags/1_0.png","icon_width":24,"icon_height":24,"num":110446,"flag":1,"note":"76年的李维嘉像96年的付豪生的","icon_desc":"新","icon_desc_color":"#ff3852","small_icon_desc":"新","small_icon_desc_color":"#ff3852","word":"76年的李维嘉像96年的付豪生的","flag_desc":"综艺","rank":25},{"icon_desc_color":"#ff3852","label_name":"新","small_icon_desc":"新","small_icon_desc_color":"#ff3852","word_scheme":"#张云龙虞书欣聚餐#","word":"张云龙虞书欣聚餐","emoticon":"","icon":"https://simg.s.weibo.com/moter/flags/1_0.png","icon_width":24,"icon_height":24,"num":105693,"flag":1,"topic_flag":1,"note":"张云龙虞书欣聚餐","icon_desc":"新","realpos":27,"rank":26},{"realpos":28,"label_name":"","topic_flag":1,"word_scheme":"#中俄安理会硬刚美国#","emoticon":"","word":"中俄安理会硬刚美国","num":97988,"flag":0,"note":"中俄安理会硬刚美国","rank":27},{"icon_desc_color":"#ff3852","label_name":"新","small_icon_desc":"新","small_icon_desc_color":"#ff3852","word_scheme":"#垫底辣孩到底长什么样#","word":"垫底辣孩到底长什么样","emoticon":"","icon":"https://simg.s.weibo.com/moter/flags/1_0.png","icon_width":24,"icon_height":24,"num":97628,"flag":1,"topic_flag":1,"note":"垫底辣孩到底长什么样","icon_desc":"新","realpos":29,"rank":28},{"icon_desc_color":"#ff3852","label_name":"新","small_icon_desc":"新","small_icon_desc_color":"#ff3852","word_scheme":"肖战品质盛典揉了多次眼睛","word":"肖战品质盛典揉了多次眼睛","emoticon":"","icon":"https://simg.s.weibo.com/moter/flags/1_0.png","icon_width":24,"icon_height":24,"num":93454,"flag":1,"topic_flag":0,"note":"肖战品质盛典揉了多次眼睛","icon_desc":"新","realpos":30,"rank":29},{"realpos":31,"label_name":"","topic_flag":1,"word_scheme":"#儿子遗体在泰医院失踪中国父亲报警#","emoticon":"","word":"儿子遗体在泰医院失踪中国父亲报警","num":92371,"flag":0,"note":"儿子遗体在泰医院失踪中国父亲报警","rank":30},{"icon_desc_color":"#ff3852","label_name":"新","small_icon_desc":"新","small_icon_desc_color":"#ff3852","word_scheme":"#男子伪造3.7万个拉环每天兑10箱啤酒#","word":"男子伪造3.7万个拉环每天兑10箱啤酒","emoticon":"","icon":"https://simg.s.weibo.com/moter/flags/1_0.png","icon_width":24,"icon_height":24,"num":87986,"flag":1,"topic_flag":1,"note":"男子伪造3.7万个拉环每天兑10箱啤酒","icon_desc":"新","realpos":32,"rank":31},{"icon_desc_color":"#ff3852","label_name":"新","small_icon_desc":"新","small_icon_desc_color":"#ff3852","word_scheme":"#多方回应被盗国保琉璃在闲鱼售卖#","word":"多方回应被盗国保琉璃在闲鱼售卖","emoticon":"","icon":"https://simg.s.weibo.com/moter/flags/1_0.png","icon_width":24,"icon_height":24,"num":84521,"flag":1,"topic_flag":1,"note":"多方回应被盗国保琉璃在闲鱼售卖","icon_desc":"新","realpos":33,"rank":32},{"realpos":34,"label_name":"","topic_flag":0,"word_scheme":"绩效 反人类","emoticon":"","word":"绩效 反人类","num":81890,"flag":0,"note":"绩效 反人类","rank":33},{"realpos":35,"label_name":"","topic_flag":1,"word_scheme":"#广电总局将公布演员番位规则#","emoticon":"","word":"广电总局将公布演员番位规则","num":81146,"flag":0,"note":"广电总局将公布演员番位规则","rank":34},{"realpos":36,"label_name":"","topic_flag":1,"word_scheme":"#痞幼做医美了#","emoticon":"","word":"痞幼做医美了","num":78978,"flag":0,"note":"痞幼做医美了","rank":35},{"realpos":37,"label_name":"","topic_flag":0,"word_scheme":"冻干草莓 农药","emoticon":"","word":"冻干草莓 农药","num":75742,"flag":0,"note":"冻干草莓 农药","rank":36},{"realpos":38,"label_name":"","topic_flag":0,"word_scheme":"沈月说不能留白鹿一个人","emoticon":"","word":"沈月说不能留白鹿一个人","flag_desc":"综艺","num":75404,"flag":0,"note":"沈月说不能留白鹿一个人","rank":37},{"realpos":39,"label_name":"","topic_flag":1,"word_scheme":"#济州航空空难一年后再现遇难者遗骸#","emoticon":"","word":"济州航空空难一年后再现遇难者遗骸","num":74317,"flag":0,"note":"济州航空空难一年后再现遇难者遗骸","rank":38},{"icon_desc_color":"#ff3852","label_name":"新","small_icon_desc":"新","small_icon_desc_color":"#ff3852","word_scheme":"#平台订房付1471元酒店仅收到618元#","word":"平台订房付1471元酒店仅收到618元","emoticon":"","icon":"https://simg.s.weibo.com/moter/flags/1_0.png","icon_width":24,"icon_height":24,"num":74017,"flag":1,"topic_flag":1,"note":"平台订房付1471元酒店仅收到618元","icon_desc":"新","realpos":40,"rank":39},{"icon_desc_color":"#ff3852","label_name":"新","small_icon_desc":"新","small_icon_desc_color":"#ff3852","word_scheme":"#男子被忘核磁共振机医院曾被罚5900万#","word":"男子被忘核磁共振机医院曾被罚5900万","emoticon":"","icon":"https://simg.s.weibo.com/moter/flags/1_0.png","icon_width":24,"icon_height":24,"num":74016,"flag":1,"topic_flag":1,"note":"男子被忘核磁共振机医院曾被罚5900万","icon_desc":"新","realpos":41,"rank":40},{"icon_desc_color":"#ff3852","label_name":"新","small_icon_desc":"新","small_icon_desc_color":"#ff3852","word_scheme":"苏醒主持人证的含金量我后知后觉","word":"苏醒主持人证的含金量我后知后觉","emoticon":"","icon":"https://simg.s.weibo.com/moter/flags/1_0.png","icon_width":24,"icon_height":24,"num":73724,"flag":1,"topic_flag":0,"note":"苏醒主持人证的含金量我后知后觉","icon_desc":"新","realpos":42,"rank":41},{"realpos":43,"label_name":"","topic_flag":0,"word_scheme":"瞿颖能不能去花少","emoticon":"","word":"瞿颖能不能去花少","num":73722,"flag":0,"note":"瞿颖能不能去花少","rank":42},{"realpos":44,"label_name":"","topic_flag":1,"word_scheme":"#国产手机涨价2000元#","emoticon":"","word":"国产手机涨价2000元","num":73714,"flag":0,"note":"国产手机涨价2000元","rank":43},{"realpos":45,"label_name":"","topic_flag":0,"word_scheme":"安崎求职浪姐真的成功了","emoticon":"","word":"安崎求职浪姐真的成功了","flag_desc":"综艺","num":73712,"flag":0,"note":"安崎求职浪姐真的成功了","rank":44},{"realpos":46,"label_name":"","topic_flag":1,"word_scheme":"#韩佳人化中国网红妆#","emoticon":"","word":"韩佳人化中国网红妆","num":73703,"flag":0,"note":"韩佳人化中国网红妆","rank":45},{"icon_desc_color":"#ff3852","label_name":"新","small_icon_desc":"新","small_icon_desc_color":"#ff3852","word_scheme":"火星日落的真实照片","word":"火星日落的真实照片","emoticon":"","icon":"https://simg.s.weibo.com/moter/flags/1_0.png","icon_width":24,"icon_height":24,"num":73702,"flag":1,"topic_flag":0,"note":"火星日落的真实照片","icon_desc":"新","realpos":47,"rank":46},{"realpos":48,"label_name":"","topic_flag":0,"word_scheme":"张晚意没到二月二就剪头了","emoticon":"","word":"张晚意没到二月二就剪头了","flag_desc":"剧集","num":73694,"flag":0,"note":"张晚意没到二月二就剪头了","rank":47},{"realpos":49,"label_name":"新","topic_flag":1,"word_scheme":"#王橹杰投篮#","emoticon":"","icon":"https://simg.s.weibo.com/moter/flags/1_0.png","icon_width":24,"icon_height":24,"num":73692,"flag":1,"note":"王橹杰投篮","icon_desc":"新","icon_desc_color":"#ff3852","small_icon_desc":"新","small_icon_desc_color":"#ff3852","word":"王橹杰投篮","flag_desc":"剧集","rank":48},{"icon_desc_color":"#ff3852","label_name":"新","small_icon_desc":"新","small_icon_desc_color":"#ff3852","word_scheme":"#BLG出征全球先锋赛#","word":"BLG出征全球先锋赛","emoticon":"","icon":"https://simg.s.weibo.com/moter/flags/1_0.png","icon_width":24,"icon_height":24,"num":73682,"flag":1,"topic_flag":1,"note":"BLG出征全球先锋赛","icon_desc":"新","realpos":50,"rank":49}]
