[{"realpos":1,"label_name":"热","topic_flag":1,"word_scheme":"#还我妈生鼻#","icon_width":24,"icon_height":24,"flag":2,"num":1377229,"icon_desc":"热","note":"还我妈生鼻","icon_desc_color":"#ff9406","flag_desc":"音乐","small_icon_desc":"热","emoticon":"","small_icon_desc_color":"#ff9406","word":"还我妈生鼻","icon":"https://simg.s.weibo.com/moter/flags/2_0.png","rank":0},{"realpos":2,"emoticon":"","icon":"https://simg.s.weibo.com/moter/flags/32768_0.png","word":"河南小伙高考529分被清华录取","flag":32768,"icon_desc_color":"#ffab5a","num":1036840,"icon_desc":"暖","note":"河南小伙高考529分被清华录取","label_name":"暖","small_icon_desc_color":"#ffab5a","small_icon_desc":"暖","topic_flag":1,"icon_height":24,"word_scheme":"#河南小伙高考529分被清华录取#","icon_width":24,"rank":1},{"realpos":3,"flag":0,"num":1024790,"note":"中国奥运项目首金高燃视频","label_name":"","topic_flag":1,"emoticon":"","word_scheme":"#中国奥运项目首金高燃视频#","word":"中国奥运项目首金高燃视频","rank":2},{"realpos":4,"emoticon":"","icon_height":24,"icon_width":24,"flag":1,"icon_desc_color":"#ff3852","num":1018707,"icon_desc":"新","note":"偶遇霍思燕带女儿喝下午茶","label_name":"新","icon":"https://simg.s.weibo.com/moter/flags/1_0.png","small_icon_desc":"新","small_icon_desc_color":"#ff3852","topic_flag":1,"word_scheme":"#偶遇霍思燕带女儿喝下午茶#","word":"偶遇霍思燕带女儿喝下午茶","rank":3},{"realpos":5,"emoticon":"","icon_height":24,"icon_width":24,"flag":1,"icon_desc_color":"#ff3852","num":998932,"icon_desc":"新","note":"台风格美在福建沿海登陆","label_name":"新","icon":"https://simg.s.weibo.com/moter/flags/1_0.png","small_icon_desc":"新","small_icon_desc_color":"#ff3852","topic_flag":1,"word_scheme":"#台风格美在福建沿海登陆#","word":"台风格美在福建沿海登陆","rank":4},{"realpos":6,"emoticon":"","icon_height":24,"icon_width":24,"flag":1,"icon_desc_color":"#ff3852","num":645041,"icon_desc":"新","note":"为啥打耳洞不会有肉被捅出来","label_name":"新","icon":"https://simg.s.weibo.com/moter/flags/1_0.png","small_icon_desc":"新","small_icon_desc_color":"#ff3852","topic_flag":1,"word_scheme":"#为啥打耳洞不会有肉被捅出来#","word":"为啥打耳洞不会有肉被捅出来","rank":5},{"dot_icon":1,"monitors":{"app":[{"type":"","third_party_click":"","third_party_show":""},{"type":"","third_party_click":"","third_party_show":""}],"pc":[{"type":"","pc_click":"","pc_show":""},{"type":"","pc_click":"","pc_show":""}]},"topic_flag":1,"icon":"https://simg.s.weibo.com/20220424_search_ads_%E5%AE%98%E5%AE%A3.png","icon_width":24,"icon_height":24,"is_ad":1,"emoticon":"","num":644895,"icon_desc":"官宣","note":"开黑吃夜宵就来海底捞","icon_desc_color":"#00b7ee","topic_ad":1,"small_icon_desc":"商","small_icon_desc_color":"#00b7ee","word":"开黑吃夜宵就来海底捞","id":246754,"icon_type":"jian","rank":5},{"realpos":7,"label_name":"新","topic_flag":0,"word_scheme":"夏之光 亲什么嘴儿啊","word":"夏之光 亲什么嘴儿啊","icon_height":24,"flag":1,"num":644822,"icon_desc":"新","note":"夏之光 亲什么嘴儿啊","icon_desc_color":"#ff3852","flag_desc":"剧集","small_icon_desc":"新","emoticon":"","small_icon_desc_color":"#ff3852","icon_width":24,"icon":"https://simg.s.weibo.com/moter/flags/1_0.png","rank":6},{"realpos":8,"emoticon":"","icon_height":24,"icon_width":24,"flag":1,"icon_desc_color":"#ff3852","num":632352,"icon_desc":"新","note":"台风登陆","label_name":"新","icon":"https://simg.s.weibo.com/moter/flags/1_0.png","small_icon_desc":"新","small_icon_desc_color":"#ff3852","topic_flag":0,"word_scheme":"台风登陆","word":"台风登陆","rank":7},{"realpos":9,"flag":0,"num":529188,"note":"九尾 手伤","label_name":"","topic_flag":0,"emoticon":"","word_scheme":"九尾 手伤","word":"九尾 手伤","rank":8},{"realpos":10,"emoticon":"","icon_height":24,"icon_width":24,"flag":1,"icon_desc_color":"#ff3852","num":421075,"icon_desc":"新","note":"TFBOYS头发梳成大人模样是凯妈做的","label_name":"新","icon":"https://simg.s.weibo.com/moter/flags/1_0.png","small_icon_desc":"新","small_icon_desc_color":"#ff3852","topic_flag":1,"word_scheme":"#TFBOYS头发梳成大人模样是凯妈做的#","word":"TFBOYS头发梳成大人模样是凯妈做的","rank":9},{"realpos":11,"flag":0,"num":405087,"note":"刘耀文头像","label_name":"","topic_flag":0,"emoticon":"","word_scheme":"刘耀文头像","word":"刘耀文头像","rank":10},{"realpos":12,"emoticon":"","icon_height":24,"icon_width":24,"flag":1,"icon_desc_color":"#ff3852","num":394082,"icon_desc":"新","note":"深圳地铁","label_name":"新","icon":"https://simg.s.weibo.com/moter/flags/1_0.png","small_icon_desc":"新","small_icon_desc_color":"#ff3852","topic_flag":0,"word_scheme":"深圳地铁","word":"深圳地铁","rank":11},{"realpos":13,"flag":0,"num":342609,"note":"密室大神版 svip还要收费","label_name":"","flag_desc":"综艺","topic_flag":0,"emoticon":"","word_scheme":"密室大神版 svip还要收费","word":"密室大神版 svip还要收费","rank":12},{"realpos":14,"flag":0,"num":341829,"note":"孙卓已被南京工业大学录取","label_name":"","topic_flag":1,"emoticon":"","word_scheme":"#孙卓已被南京工业大学录取#","word":"孙卓已被南京工业大学录取","rank":13},{"realpos":15,"emoticon":"","icon_height":24,"icon_width":24,"flag":1,"icon_desc_color":"#ff3852","num":328574,"icon_desc":"新","note":"杨旭文 唐诡2嫡掌子","label_name":"新","icon":"https://simg.s.weibo.com/moter/flags/1_0.png","small_icon_desc":"新","small_icon_desc_color":"#ff3852","topic_flag":0,"word_scheme":"杨旭文 唐诡2嫡掌子","word":"杨旭文 唐诡2嫡掌子","rank":14},{"realpos":16,"flag":0,"num":307931,"monitors":{"app":{},"pc":{}},"label_name":"","emoticon":"","note":"20万内唯一搭载华为智驾SUV","topic_flag":1,"id":247044,"word_scheme":"#20万内唯一搭载华为智驾SUV#","word":"20万内唯一搭载华为智驾SUV","rank":15},{"realpos":17,"flag":0,"num":294048,"monitors":{"app":{},"pc":{}},"label_name":"","emoticon":"","note":"为什么260万用户都选比亚迪宋","topic_flag":1,"id":246676,"word_scheme":"#为什么260万用户都选比亚迪宋#","word":"为什么260万用户都选比亚迪宋","rank":16},{"realpos":18,"emoticon":"","icon_height":24,"icon_width":24,"flag":1,"icon_desc_color":"#ff3852","num":288439,"icon_desc":"新","note":"台风格美影响或波及10余省份","label_name":"新","icon":"https://simg.s.weibo.com/moter/flags/1_0.png","small_icon_desc":"新","small_icon_desc_color":"#ff3852","topic_flag":1,"word_scheme":"#台风格美影响或波及10余省份#","word":"台风格美影响或波及10余省份","rank":17},{"realpos":19,"flag":0,"num":286949,"note":"中国游泳队身上全是火罐印","label_name":"","topic_flag":1,"emoticon":"","word_scheme":"#中国游泳队身上全是火罐印#","word":"中国游泳队身上全是火罐印","rank":18},{"realpos":20,"emoticon":"","icon_height":24,"icon_width":24,"flag":1,"icon_desc_color":"#ff3852","num":268861,"icon_desc":"新","note":"刘梓晨","label_name":"新","icon":"https://simg.s.weibo.com/moter/flags/1_0.png","small_icon_desc":"新","small_icon_desc_color":"#ff3852","topic_flag":0,"word_scheme":"刘梓晨","word":"刘梓晨","rank":19},{"realpos":21,"flag":0,"num":262871,"note":"真的很讨厌外卖点到液体勺","label_name":"","topic_flag":1,"emoticon":"","word_scheme":"#真的很讨厌外卖点到液体勺#","word":"真的很讨厌外卖点到液体勺","rank":20},{"realpos":22,"emoticon":"","icon_height":24,"icon_width":24,"flag":1,"icon_desc_color":"#ff3852","num":256654,"icon_desc":"新","note":"亲戚催婚时好像说漏嘴了","label_name":"新","icon":"https://simg.s.weibo.com/moter/flags/1_0.png","small_icon_desc":"新","small_icon_desc_color":"#ff3852","topic_flag":1,"word_scheme":"#亲戚催婚时好像说漏嘴了#","word":"亲戚催婚时好像说漏嘴了","rank":21},{"realpos":23,"flag":0,"num":243893,"note":"美国男子奸杀8岁女孩抛尸垃圾箱","label_name":"","topic_flag":1,"emoticon":"","word_scheme":"#美国男子奸杀8岁女孩抛尸垃圾箱#","word":"美国男子奸杀8岁女孩抛尸垃圾箱","rank":22},{"realpos":24,"label_name":"新","topic_flag":1,"word_scheme":"#黄明昊在十个勤天中都i起来了#","word":"黄明昊在十个勤天中都i起来了","icon_height":24,"flag":1,"num":224407,"icon_desc":"新","note":"黄明昊在十个勤天中都i起来了","icon_desc_color":"#ff3852","flag_desc":"综艺","small_icon_desc":"新","emoticon":"","small_icon_desc_color":"#ff3852","icon_width":24,"icon":"https://simg.s.weibo.com/moter/flags/1_0.png","rank":23},{"realpos":25,"flag":0,"num":223228,"monitors":{"app":{},"pc":{}},"label_name":"","emoticon":"","note":"手机成为电影短片设备主力军","topic_flag":1,"id":246812,"word_scheme":"#手机成为电影短片设备主力军#","word":"手机成为电影短片设备主力军","rank":24},{"realpos":26,"emoticon":"","icon_height":24,"icon_width":24,"flag":1,"icon_desc_color":"#ff3852","num":223176,"icon_desc":"新","note":"离岸人民币兑美元升破7.21","label_name":"新","icon":"https://simg.s.weibo.com/moter/flags/1_0.png","small_icon_desc":"新","small_icon_desc_color":"#ff3852","topic_flag":1,"word_scheme":"#离岸人民币兑美元升破7.21#","word":"离岸人民币兑美元升破7.21","rank":25},{"realpos":27,"label_name":"新","topic_flag":0,"word_scheme":"许凯彭昱畅陈哲远各有各的好笑","word":"许凯彭昱畅陈哲远各有各的好笑","icon_height":24,"flag":1,"num":223148,"icon_desc":"新","note":"许凯彭昱畅陈哲远各有各的好笑","icon_desc_color":"#ff3852","flag_desc":"综艺","small_icon_desc":"新","emoticon":"","small_icon_desc_color":"#ff3852","icon_width":24,"icon":"https://simg.s.weibo.com/moter/flags/1_0.png","rank":26},{"realpos":28,"flag":0,"num":222621,"note":"台风格美登陆福建位置又变了","label_name":"","topic_flag":1,"emoticon":"","word_scheme":"#台风格美登陆福建位置又变了#","word":"台风格美登陆福建位置又变了","rank":27},{"realpos":29,"flag":0,"num":213491,"note":"披荆斩棘4返场哥哥投票","label_name":"","flag_desc":"综艺","topic_flag":1,"emoticon":"","word_scheme":"#披荆斩棘4返场哥哥投票#","word":"披荆斩棘4返场哥哥投票","rank":28},{"realpos":30,"label_name":"新","topic_flag":1,"word_scheme":"#终于知道刘昊然去年为什么那么瘦了#","word":"终于知道刘昊然去年为什么那么瘦了","icon_height":24,"flag":1,"num":212961,"icon_desc":"新","note":"终于知道刘昊然去年为什么那么瘦了","icon_desc_color":"#ff3852","flag_desc":"电影","small_icon_desc":"新","emoticon":"","small_icon_desc_color":"#ff3852","icon_width":24,"icon":"https://simg.s.weibo.com/moter/flags/1_0.png","rank":29},{"realpos":31,"flag":0,"num":199187,"note":"密室大逃脱 举报","label_name":"","flag_desc":"综艺","topic_flag":0,"emoticon":"","word_scheme":"密室大逃脱 举报","word":"密室大逃脱 举报","rank":30},{"realpos":32,"label_name":"新","topic_flag":0,"word_scheme":"田嘉瑞到底什么是真的","word":"田嘉瑞到底什么是真的","icon_height":24,"flag":1,"num":192615,"icon_desc":"新","note":"田嘉瑞到底什么是真的","icon_desc_color":"#ff3852","flag_desc":"综艺","small_icon_desc":"新","emoticon":"","small_icon_desc_color":"#ff3852","icon_width":24,"icon":"https://simg.s.weibo.com/moter/flags/1_0.png","rank":31},{"realpos":33,"flag":0,"num":179253,"note":"巴黎奥运 告白气球塌房","label_name":"","topic_flag":0,"emoticon":"","word_scheme":"巴黎奥运 告白气球塌房","word":"巴黎奥运 告白气球塌房","rank":32},{"realpos":34,"flag":0,"num":178439,"note":"杨幂村妇造型路透","label_name":"","flag_desc":"剧集","topic_flag":1,"emoticon":"","word_scheme":"#杨幂村妇造型路透#","word":"杨幂村妇造型路透","rank":33},{"realpos":35,"flag":0,"num":177960,"monitors":{"app":{},"pc":{}},"label_name":"","emoticon":"","note":"欧米茄宣传片好燃","topic_flag":1,"id":247046,"word_scheme":"#欧米茄宣传片好燃#","word":"欧米茄宣传片好燃","rank":34},{"realpos":36,"emoticon":"","icon_height":24,"icon_width":24,"flag":1,"icon_desc_color":"#ff3852","num":177748,"icon_desc":"新","note":"小狗遇见心软的神了","label_name":"新","icon":"https://simg.s.weibo.com/moter/flags/1_0.png","small_icon_desc":"新","small_icon_desc_color":"#ff3852","topic_flag":1,"word_scheme":"#小狗遇见心软的神了#","word":"小狗遇见心软的神了","rank":35},{"realpos":37,"flag":0,"num":177594,"note":"樊振东 死亡下半区","label_name":"","topic_flag":0,"emoticon":"","word_scheme":"樊振东 死亡下半区","word":"樊振东 死亡下半区","rank":36},{"realpos":38,"flag":0,"num":172470,"note":"刘昊然自曝数学成绩","label_name":"","flag_desc":"电影","topic_flag":1,"emoticon":"","word_scheme":"#刘昊然自曝数学成绩#","word":"刘昊然自曝数学成绩","rank":37},{"realpos":39,"flag":0,"num":167032,"note":"南工大欢迎孙卓","label_name":"","topic_flag":1,"emoticon":"","word_scheme":"#南工大欢迎孙卓#","word":"南工大欢迎孙卓","rank":38},{"realpos":40,"flag":0,"num":166475,"note":"应聘时HR拿着我的简历在手抖","label_name":"","topic_flag":1,"emoticon":"","word_scheme":"#应聘时HR拿着我的简历在手抖#","word":"应聘时HR拿着我的简历在手抖","rank":39},{"realpos":41,"emoticon":"","icon_height":24,"icon_width":24,"flag":1,"icon_desc_color":"#ff3852","num":158867,"icon_desc":"新","note":"老破小现在值得入手吗","label_name":"新","icon":"https://simg.s.weibo.com/moter/flags/1_0.png","small_icon_desc":"新","small_icon_desc_color":"#ff3852","topic_flag":1,"word_scheme":"#老破小现在值得入手吗#","word":"老破小现在值得入手吗","rank":40},{"realpos":42,"emoticon":"","icon_height":24,"icon_width":24,"flag":1,"icon_desc_color":"#ff3852","num":155987,"icon_desc":"新","note":"与辉同行总销售额超42亿","label_name":"新","icon":"https://simg.s.weibo.com/moter/flags/1_0.png","small_icon_desc":"新","small_icon_desc_color":"#ff3852","topic_flag":1,"word_scheme":"#与辉同行总销售额超42亿#","word":"与辉同行总销售额超42亿","rank":41},{"realpos":43,"flag":0,"num":145298,"note":"闵熙珍说郑秀晶抄袭她","label_name":"","topic_flag":1,"emoticon":"","word_scheme":"#闵熙珍说郑秀晶抄袭她#","word":"闵熙珍说郑秀晶抄袭她","rank":42},{"realpos":44,"emoticon":"","icon_height":24,"icon_width":24,"flag":1,"icon_desc_color":"#ff3852","num":139269,"icon_desc":"新","note":"宝诗龙活动","label_name":"新","icon":"https://simg.s.weibo.com/moter/flags/1_0.png","small_icon_desc":"新","small_icon_desc_color":"#ff3852","topic_flag":0,"word_scheme":"宝诗龙活动","word":"宝诗龙活动","rank":43},{"realpos":45,"flag":0,"num":139053,"note":"道枝骏佑直播","label_name":"","topic_flag":1,"emoticon":"","word_scheme":"#道枝骏佑直播#","word":"道枝骏佑直播","rank":44},{"realpos":46,"emoticon":"","icon_height":24,"icon_width":24,"flag":1,"icon_desc_color":"#ff3852","num":138388,"icon_desc":"新","note":"李昊卓沅 真假球王","label_name":"新","icon":"https://simg.s.weibo.com/moter/flags/1_0.png","small_icon_desc":"新","small_icon_desc_color":"#ff3852","topic_flag":0,"word_scheme":"李昊卓沅 真假球王","word":"李昊卓沅 真假球王","rank":45},{"realpos":47,"flag":0,"num":137111,"note":"种地吧","label_name":"","flag_desc":"综艺","topic_flag":0,"emoticon":"","word_scheme":"种地吧","word":"种地吧","rank":46},{"realpos":48,"label_name":"新","topic_flag":0,"word_scheme":"陶喆抢票","word":"陶喆抢票","icon_height":24,"flag":1,"num":131260,"icon_desc":"新","note":"陶喆抢票","icon_desc_color":"#ff3852","flag_desc":"演出","small_icon_desc":"新","emoticon":"","small_icon_desc_color":"#ff3852","icon_width":24,"icon":"https://simg.s.weibo.com/moter/flags/1_0.png","rank":47},{"realpos":49,"emoticon":"","icon_height":24,"icon_width":24,"flag":1,"icon_desc_color":"#ff3852","num":128492,"icon_desc":"新","note":"孙海洋晒孙卓录取通知书","label_name":"新","icon":"https://simg.s.weibo.com/moter/flags/1_0.png","small_icon_desc":"新","small_icon_desc_color":"#ff3852","topic_flag":1,"word_scheme":"#孙海洋晒孙卓录取通知书#","word":"孙海洋晒孙卓录取通知书","rank":48},{"realpos":50,"flag":0,"num":126330,"note":"宁肯赔3万也不道歉","label_name":"","topic_flag":1,"emoticon":"","word_scheme":"#宁肯赔3万也不道歉#","word":"宁肯赔3万也不道歉","rank":49}]
